MANIFEST.in
NEWS.txt
README.rst
setup.py
src/bigdoorkit/__init__.py
src/bigdoorkit/client.py
src/bigdoorkit/exc.py
src/bigdoorkit.egg-info/PKG-INFO
src/bigdoorkit.egg-info/SOURCES.txt
src/bigdoorkit.egg-info/dependency_links.txt
src/bigdoorkit.egg-info/not-zip-safe
src/bigdoorkit.egg-info/requires.txt
src/bigdoorkit.egg-info/top_level.txt
src/bigdoorkit/resources/__init__.py
src/bigdoorkit/resources/award.py
src/bigdoorkit/resources/base.py
src/bigdoorkit/resources/currency.py
src/bigdoorkit/resources/good.py
src/bigdoorkit/resources/level.py
src/bigdoorkit/resources/user.py