Metadata-Version: 1.0
Name: bigdoorkit
Version: 0.1.4
Summary: Client library for the BigDoor API, based on RESTkit
Home-page: http://bitbucket.org/splee/bigdoorkit
Author: Lee McFadden
Author-email: spleeman@gmail.com
License: MIT
Platform: UNKNOWN
Classifier: Development Status :: 4 - Beta
Classifier: Intended Audience :: Developers
Classifier: License :: OSI Approved :: MIT License
Classifier: Operating System :: OS Independent
